agenthive/__init__.py
agenthive/cli.py
agenthive/version.py
agenthive/core/__init__.py
agenthive/core/coordinator.py
agenthive/core/enhanced_coordinator.py
agenthive/core/in_memory_task_manager.py
agenthive/core/registry.py
agenthive/core/task.py
agenthive/core/worker.py
agenthive/core/heartbeat/__init__.py
agenthive/core/heartbeat/constants.py
agenthive/core/heartbeat/manager.py
agenthive/core/heartbeat/models.py
agenthive/core/heartbeat/monitor.py
agenthive/core/heartbeat/operations.py
agenthive/core/heartbeat/sender.py
agenthive/db/__init__.py
agenthive/db/connection.py
agenthive/db/operations.py
agenthive/db/adapters/__init__.py
agenthive/db/adapters/base.py
agenthive/db/adapters/sqlalchemy.py
agenthive/db/models/__init__.py
agenthive/db/models/heartbeat.py
agenthive/db/models/system.py
agenthive/db/models/task.py
agenthive/db/models/worker.py
agenthive/service/__init__.py
agenthive/service/coordinator/__init__.py
agenthive/service/coordinator/main.py
agenthive/service/monitor/__init__.py
agenthive/service/monitor/backend/__init__.py
agenthive/service/monitor/backend/main.py
agenthive/service/monitor/backend/templates/index.html
agenthive/service/worker/__init__.py
agenthive/service/worker/main.py
agenthive/tasks/__init__.py
agenthive/templates/docker/docker-compose.base.yml
agenthive/templates/docker/docker-compose.yml
agenthive/templates/docker/coordinator/Dockerfile
agenthive/templates/docker/coordinator/config/app-coordinator.conf
agenthive/templates/docker/coordinator/config/coordinator.env
agenthive/templates/docker/coordinator/config/supervisord.conf
agenthive/templates/docker/monitor/Dockerfile
agenthive/templates/docker/monitor/config/app-monitor.conf
agenthive/templates/docker/monitor/config/monitor.env
agenthive/templates/docker/monitor/config/supervisord.conf
agenthive/templates/docker/postgres/init.sql
agenthive/templates/docker/postgres/postgresql.conf
agenthive/templates/docker/redis/redis.conf
agenthive/templates/docker/worker/Dockerfile
agenthive-1.0.202506050705.dist-info/licenses/LICENSE
agenthive-1.0.202506050705.dist-info/METADATA
agenthive-1.0.202506050705.dist-info/WHEEL
agenthive-1.0.202506050705.dist-info/entry_points.txt
agenthive-1.0.202506050705.dist-info/top_level.txt
agenthive-1.0.202506050705.dist-info/RECORD
