Metadata-Version: 2.4
Name: AgentHive
Version: 1.0.202506050705
Summary: AgentHive is a flexible, Python-based service framework for managing distributed task execution.
Home-page: https://github.com/changyy/py-AgentHive
Author: changyy
Author-email: changyy.csie@gmail.com
Project-URL: Bug Tracker, https://github.com/changyy/py-AgentHive/issues
Project-URL: Documentation, https://py-agenthiveflow.readthedocs.io
Project-URL: Source Code, https://github.com/changyy/py-AgentHive
Classifier: Development Status :: 3 - Alpha
Classifier: Intended Audience :: Developers
Classifier: License :: OSI Approved :: MIT License
Classifier: Programming Language :: Python :: 3
Classifier: Programming Language :: Python :: 3.12
Classifier: Operating System :: OS Independent
Classifier: Topic :: Software Development :: Libraries :: Application Frameworks
Classifier: Topic :: Scientific/Engineering :: Artificial Intelligence
Classifier: Topic :: Internet :: WWW/HTTP :: Indexing/Search
Requires-Python: >=3.12
License-File: LICENSE
Requires-Dist: pydantic>=2.10.6
Requires-Dist: sqlalchemy>=2.0.38
Requires-Dist: asyncpg>=0.30.0
Requires-Dist: aiosqlite==0.21.0
Requires-Dist: pytz==2025.1
Requires-Dist: python-dateutil==2.9.0.post0
Requires-Dist: redis>=5.2.1
Requires-Dist: hiredis>=3.1.0
Requires-Dist: aiohttp>=3.11.13
Requires-Dist: httpx>=0.28.1
Requires-Dist: click>=8.1.8
Requires-Dist: python-dotenv>=1.0.1
Requires-Dist: pyyaml>=6.0.2
Requires-Dist: psutil>=7.0.0
Requires-Dist: uvicorn==0.34.0
Requires-Dist: supervisor==4.2.5
Requires-Dist: beautifulsoup4==4.12.2
Requires-Dist: requests==2.31.0
Requires-Dist: supervisor==4.2.5
Requires-Dist: uvicorn==0.34.0
Requires-Dist: fastapi==0.115.11
Requires-Dist: starlette==0.46.1
Requires-Dist: websockets==15.0.1
Requires-Dist: asyncpg==0.30.0
Requires-Dist: jinja2==3.1.6
Requires-Dist: python-multipart==0.0.20
Requires-Dist: prometheus-client==0.21.1
Requires-Dist: matplotlib==3.10.1
Requires-Dist: pandas==2.2.3
Provides-Extra: dev
Requires-Dist: pydantic>=2.10.6; extra == "dev"
Requires-Dist: sqlalchemy>=2.0.38; extra == "dev"
Requires-Dist: asyncpg>=0.30.0; extra == "dev"
Requires-Dist: aiosqlite==0.21.0; extra == "dev"
Requires-Dist: pytz==2025.1; extra == "dev"
Requires-Dist: python-dateutil==2.9.0.post0; extra == "dev"
Requires-Dist: redis>=5.2.1; extra == "dev"
Requires-Dist: hiredis>=3.1.0; extra == "dev"
Requires-Dist: aiohttp>=3.11.13; extra == "dev"
Requires-Dist: httpx>=0.28.1; extra == "dev"
Requires-Dist: click>=8.1.8; extra == "dev"
Requires-Dist: python-dotenv>=1.0.1; extra == "dev"
Requires-Dist: pyyaml>=6.0.2; extra == "dev"
Requires-Dist: psutil>=7.0.0; extra == "dev"
Requires-Dist: uvicorn==0.34.0; extra == "dev"
Requires-Dist: supervisor==4.2.5; extra == "dev"
Requires-Dist: beautifulsoup4==4.12.2; extra == "dev"
Requires-Dist: requests==2.31.0; extra == "dev"
Requires-Dist: supervisor==4.2.5; extra == "dev"
Requires-Dist: uvicorn==0.34.0; extra == "dev"
Requires-Dist: fastapi==0.115.11; extra == "dev"
Requires-Dist: starlette==0.46.1; extra == "dev"
Requires-Dist: websockets==15.0.1; extra == "dev"
Requires-Dist: asyncpg==0.30.0; extra == "dev"
Requires-Dist: jinja2==3.1.6; extra == "dev"
Requires-Dist: python-multipart==0.0.20; extra == "dev"
Requires-Dist: prometheus-client==0.21.1; extra == "dev"
Requires-Dist: matplotlib==3.10.1; extra == "dev"
Requires-Dist: pandas==2.2.3; extra == "dev"
Requires-Dist: pytest==8.3.5; extra == "dev"
Requires-Dist: pytest-asyncio==0.25.3; extra == "dev"
Requires-Dist: pytest-cov==6.0.0; extra == "dev"
Requires-Dist: pytest-mock==3.14.0; extra == "dev"
Requires-Dist: pytest-xdist==3.6.1; extra == "dev"
Requires-Dist: hypothesis==6.128.2; extra == "dev"
Requires-Dist: requests==2.32.3; extra == "dev"
Requires-Dist: respx==0.22.0; extra == "dev"
Requires-Dist: alembic==1.15.1; extra == "dev"
Requires-Dist: fakeredis==2.27.0; extra == "dev"
Requires-Dist: black==25.1.0; extra == "dev"
Requires-Dist: isort==6.0.1; extra == "dev"
Requires-Dist: mypy==1.15.0; extra == "dev"
Requires-Dist: flake8==7.1.2; extra == "dev"
Dynamic: author
Dynamic: author-email
Dynamic: classifier
Dynamic: description
Dynamic: description-content-type
Dynamic: home-page
Dynamic: license-file
Dynamic: project-url
Dynamic: provides-extra
Dynamic: requires-dist
Dynamic: requires-python
Dynamic: summary
